    <Sections Version="437">
  <Section Dynamic="0" MaxRows="0">
    <Items>
      <Item Value="0###101###Thành Phố Hà Nội" />
      <Item Value="0###103###Thành Phố Hải Phòng" />
      <Item Value="0###107###Tỉnh Hải Dương" />
      <Item Value="0###109###Tỉnh Hưng Yên" />
      <Item Value="0###111###Tỉnh Hà Nam" />
      <Item Value="0###113###Tỉnh Nam Định" />
      <Item Value="0###115###Tỉnh Thái Bình" />
      <Item Value="0###117###Tỉnh Ninh Bình" />
      <Item Value="0###201###Tỉnh Hà Giang" />
      <Item Value="0###203###Tỉnh Cao Bằng" />
      <Item Value="0###205###Tỉnh Lào Cai" />
      <Item Value="0###207###Tỉnh Bắc Kạn" />
      <Item Value="0###209###Tỉnh Lạng Sơn" />
      <Item Value="0###211###Tỉnh Tuyên Quang" />
      <Item Value="0###213###Tỉnh Yên Bái" />
      <Item Value="0###215###Tỉnh Thái Nguyên" />
      <Item Value="0###217###Tỉnh Phú Thọ" />
      <Item Value="0###219###Tỉnh Vĩnh Phúc" />
      <Item Value="0###221###Tỉnh Bắc Giang" />
      <Item Value="0###223###Tỉnh Bắc Ninh" />
      <Item Value="0###225###Tỉnh Quảng Ninh" />
      <Item Value="0###301###Tỉnh Điện Biên" />
      <Item Value="0###302###Tỉnh Lai Châu" />
      <Item Value="0###303###Tỉnh Sơn La" />
      <Item Value="0###305###Tỉnh Hòa Bình" />
      <Item Value="0###401###Tỉnh Thanh Hoá" />
      <Item Value="0###403###Tỉnh Nghệ An" />
      <Item Value="0###405###Tỉnh Hà Tĩnh" />
      <Item Value="0###407###Tỉnh Quảng Bình" />
      <Item Value="0###409###Tỉnh Quảng Trị" />
      <Item Value="0###411###Tỉnh Thừa Thiên - Huế" />
      <Item Value="0###501###Tỉnh Đà Nẵng" />
      <Item Value="0###503###Tỉnh Quảng Nam" />
      <Item Value="0###505###Tỉnh Quảng Ngãi" />
      <Item Value="0###507###Tỉnh Bình Định" />
      <Item Value="0###509###Tỉnh Phú Yên" />
      <Item Value="0###511###Tỉnh Khánh Hòa" />
      <Item Value="0###601###Tỉnh Kon Tum" />
      <Item Value="0###603###Tỉnh Gia Lai" />
      <Item Value="0###605###Tỉnh Đắk Lắk" />
      <Item Value="0###606###Tỉnh Đắk Nông" />
      <Item Value="0###701###Thành Phố Hồ Chí Minh" />
      <Item Value="0###703###Tỉnh Lâm Đồng" />
      <Item Value="0###705###Tỉnh Ninh Thuận" />
      <Item Value="0###707###Tỉnh Bình Phước" />
      <Item Value="0###709###Tỉnh Tây Ninh" />
      <Item Value="0###711###Tỉnh Bình Dương" />
      <Item Value="0###713###Tỉnh Đồng Nai" />
      <Item Value="0###715###Tỉnh Bình Thuận" />
      <Item Value="0###717###Tỉnh Bà Rịa - Vũng Tàu" />
      <Item Value="0###801###Tỉnh Long An" />
      <Item Value="0###803###Tỉnh Đồng Tháp" />
      <Item Value="0###805###Tỉnh An Giang" />
      <Item Value="0###807###Tỉnh Tiền Giang" />
      <Item Value="0###809###Tỉnh Vĩnh Long" />
      <Item Value="0###811###Tỉnh Bến Tre" />
      <Item Value="0###813###Tỉnh Kiên Giang" />
      <Item Value="0###815###Thành Phố Cần Thơ" />
      <Item Value="0###816###Tỉnh Hậu Giang" />
      <Item Value="0###817###Tỉnh Trà Vinh" />
      <Item Value="0###819###Tỉnh Sóc Trăng" />
      <Item Value="0###821###Tỉnh Bạc Liêu" />
      <Item Value="0###823###Tỉnh Cà Mau" />
      <Item Value ="1###999###Khác" />
    </Items>
  </Section>
</Sections>